LICENSE
README.md
bitcoin_peer_rotate/__init__.py
bitcoin_peer_rotate/bitcoin_peer_rotate.py
bitcoin_peer_rotate-0.0.1.dist-info/METADATA
bitcoin_peer_rotate-0.0.1.dist-info/WHEEL
bitcoin_peer_rotate-0.0.1.dist-info/entry_points.txt
bitcoin_peer_rotate-0.0.1.dist-info/licenses/LICENSE
bitcoin_peer_rotate-0.0.1.dist-info/RECORD
