Metadata-Version: 2.1
Name: bitcoin-peer-rotate
Version: 0.0.1
Summary: Rotate peers for local Bitcoin Core node.
Project-URL: Homepage, https://github.com/ayeowch/bitcoin-peer-rotate
Project-URL: Bug Tracker, https://github.com/ayeowch/bitcoin-peer-rotate/issues
Author-email: Addy Yeow <ayeowch@gmail.com>
License-File: LICENSE
Classifier: Intended Audience :: Developers
Classifier: License :: OSI Approved :: MIT License
Classifier: Operating System :: OS Independent
Classifier: Programming Language :: Python
Classifier: Programming Language :: Python :: 3
Classifier: Topic :: System :: Networking
Classifier: Topic :: System :: Systems Administration
Requires-Python: >=3.11
Requires-Dist: python-dotenv
Requires-Dist: requests
